h3roku
