Metadata-Version: 1.0
Name: h3roku
Version: 0.2.0
Summary: Some description.
Home-page: http://github.com/vandenberghinc/h3roku
Author: Daan van den Bergh
Author-email: vandenberghinc.contact@gmail.com
License: MIT
Platform: UNKNOWN
